mrchead/__init__.py
mrchead/_version.py
mrchead/mrchead.py
mrchead-0.0.2.dist-info/LICENSE
mrchead-0.0.2.dist-info/METADATA
mrchead-0.0.2.dist-info/WHEEL
mrchead-0.0.2.dist-info/entry_points.txt
mrchead-0.0.2.dist-info/top_level.txt
mrchead-0.0.2.dist-info/RECORD
